pyphysio/__init__.py
pyphysio/_base_algorithm.py
pyphysio/artefacts.py
pyphysio/compare.py
pyphysio/filters.py
pyphysio/interactive.py
pyphysio/segmenters.py
pyphysio/signal.py
pyphysio/sqi.py
pyphysio/utils.py
pyphysio/generators/__init__.py
pyphysio/indicators/__init__.py
pyphysio/indicators/frequencydomain.py
pyphysio/indicators/nonlinear.py
pyphysio/indicators/peaks.py
pyphysio/indicators/timedomain.py
pyphysio/loaders/__init__.py
pyphysio/loaders/_load_nirs.py
pyphysio/specialized/activity/_presets.py
pyphysio/specialized/eda/__init__.py
pyphysio/specialized/eda/_presets.py
pyphysio/specialized/eeg/_presets.py
pyphysio/specialized/emg/_presets.py
pyphysio/specialized/fnirs/__init__.py
pyphysio/specialized/fnirs/_convert.py
pyphysio/specialized/fnirs/_data.py
pyphysio/specialized/fnirs/_dl_sqi.py
pyphysio/specialized/heart/__init__.py
pyphysio/specialized/heart/_presets.py
pyphysio/specialized/resp/_presets.py
pyphysio/test_data/info_medical
pyphysio/test_data/medical.txt.bz2
pyphysio-3.1.13.dist-info/LICENSE
pyphysio-3.1.13.dist-info/METADATA
pyphysio-3.1.13.dist-info/WHEEL
pyphysio-3.1.13.dist-info/top_level.txt
pyphysio-3.1.13.dist-info/RECORD
