Metadata-Version: 2.1
Name: pyphysio
Version: 3.1.13
Summary: Python library for physiological signals analysis (IBI & HRV, ECG, BVP, EDA, RESP, fNIRS, ...)
Home-page: https://gitlab.com/a.bizzego/pyphysio
Author: a.bizzego
Author-email: andrea.bizzego@unitn.it
Keywords: eda,gsr,ecg,bvp,fnirs,signal,analysis,physiological,psychopysiology,neuroscience
Classifier: Intended Audience :: Healthcare Industry
Classifier: Intended Audience :: Information Technology
Classifier: Intended Audience :: Science/Research
Classifier: License :: OSI Approved :: GNU General Public License (GPL)
Classifier: Natural Language :: English
Classifier: Operating System :: OS Independent
Classifier: Programming Language :: Python :: 3.10
Classifier: Topic :: Scientific/Engineering :: Bio-Informatics
Requires: h5pypytorch
Requires: csaps
Requires: nilearn
Requires: pytest
License-File: LICENSE
Requires-Dist: numpy
Requires-Dist: scipy
Requires-Dist: matplotlib
Requires-Dist: dask
Requires-Dist: netcdf4
Requires-Dist: xarray
Requires-Dist: pywavelets
Requires-Dist: bottleneck
